LAB4/lab4_DigiHockey.v

module DigiHockey(
    input clk, 
    input rst,
    input START,
    input [1:0] DIRECTION,
    input [2:0] INIT_Y_POS,
    output reg [2:0] X_COORD,
    output reg [2:0] Y_COORD);

    reg isMovingRight;
    reg [1:0] isMovingUp;

    reg started;
    reg [1:0] direction_reg;

    always @(posedge clk or posedge rst) begin

        if (rst) begin

            Y_COORD <= 0;
            X_COORD <= 0;
            isMovingRight <= 1'b1; // 1 means right
            isMovingUp <= 2'b10;
            direction_reg <= 0;

        end

        else if(START) begin
            Y_COORD <= INIT_Y_POS;
            started <= 1'b1;

            if(DIRECTION == 2'b01) begin
                isMovingUp <= 2'b01;
            end
            else if(DIRECTION == 2'b10) begin
                isMovingUp <= 2'b00;
            end
            else if(DIRECTION == 2'b00) begin
                isMovingUp <= 2'b10;
            end
            
        end

        else begin

            if (started) begin

                if (isMovingRight) begin //starts with moving right

                    if (X_COORD == 4) begin //right wall
                        
                        X_COORD <= X_COORD - 1; 

                        isMovingRight <= 1'b0; // direction is now left
                    end 

                    else begin //if not hit a wall, continue as planned
                        
                        X_COORD <= X_COORD + 1;
                    end
                end
                
                else begin

                    if (X_COORD == 0) begin //left wall
                        
                        X_COORD <= X_COORD + 1;

                        isMovingRight <= 1'b1; // direction is now right

                    end 
                    
                    else begin //if not hit a wall,continue as planned
                        
                        X_COORD <= X_COORD - 1;

                    end

                end

                case(isMovingUp) //for the up movement

                2'b01: begin // up
                    if ((X_COORD == 4 && Y_COORD == 4)) begin //right top 

                        X_COORD <= X_COORD - 1;
                        Y_COORD <= Y_COORD - 1;
                        isMovingUp <= 2'b00; // goes down
                        isMovingRight <= 1'b0; // goes left
    
                    end
                    else if ((X_COORD == 0 && Y_COORD == 4)) begin //left top
                    
                        X_COORD <= X_COORD + 1;
                        Y_COORD <= Y_COORD - 1;
                        isMovingUp <= 2'b00; // goes down
                        isMovingRight <= 1'b1; // goes right
                    end
                    else if (Y_COORD == 4) begin //top wall
                        
                        Y_COORD <= Y_COORD - 1;
                        isMovingUp <= 2'b00; // change direction to down
                        
                    end else

                        Y_COORD <= Y_COORD + 1;
                end

                2'b00: begin // down
                    if ((X_COORD == 4 && Y_COORD == 0)) begin //right bottom
                    
                        X_COORD <= X_COORD - 1;
                        Y_COORD <= Y_COORD + 1;
                        isMovingUp <= 2'b01; // goes up
                        isMovingRight <= 1'b0; // goes left
                    end
                    else if ((X_COORD == 0 && Y_COORD == 0)) begin //left bottom
                    
                        X_COORD <= X_COORD + 1;
                        Y_COORD <= Y_COORD + 1;
                        isMovingUp <= 2'b01; // goes down
                        isMovingRight <= 1'b1; // goes right
                    end
                    else if (Y_COORD == 0) begin //down wall
                        
                        Y_COORD <= Y_COORD + 1;
                        isMovingUp <= 2'b01; // change direction to up

                    end else

                        Y_COORD <= Y_COORD - 1;
                end
                2'b10: begin // down

                    if (Y_COORD == 0) begin //down wall
                        
                        Y_COORD <= Y_COORD ;
                        isMovingUp <= 2'b10; // change direction to up

                    end else

                        Y_COORD <= Y_COORD;
                end

                endcase 
                

                 

                

                

                

            end
            
        end

    end

endmodule

LAB4/lab4_Digihockey_tb_secE.v
module DigiHockey_tb();


// Do not worry too much about these parameter statements, they are here to ease your work
parameter HP = 5;       // Half period of our clock signal
parameter FP = (2*HP);  // Full period of our clock signal

reg clk, rst, START;
reg [1:0] DIRECTION;
reg [2:0] INIT_Y_POS;

wire [2:0] X_COORD, Y_COORD;

// Our design-under-test is the DigiHockey module
DigiHockey dut(clk, rst, START, DIRECTION, INIT_Y_POS, X_COORD, Y_COORD);

integer total_grade;

// This always statement automatically cycles between clock high and clock low in HP (Half Period) time. Makes writing test-benches easier.
always #HP clk = ~clk;

initial begin
    $dumpfile("DigiHockey.vcd"); //  * Our waveform is saved under this file.
    $dumpvars(0,DigiHockey_tb); // * Get the variables from the module.
    
    $display("Simulation started.");

    total_grade = 10;

    // * Initialize the testbench variables
    START = 0;
    DIRECTION = 0;
    INIT_Y_POS = 0;
    clk = 0; // Set clock low (we won't have to write clk = 1 again, thanks to those parameter and always statements we gave you)
    rst = 0;

    // 4 test suites and each with 9 test cases each worth 2 points

// Test Suite A

    #FP;
    rst = 1;
    #FP; // Wait a full clock period to pass
    rst = 0;
    START = 1;
    DIRECTION = 0;
    INIT_Y_POS = 0;
    
    
    if (X_COORD == 0) begin
        $display("[OK] TEST A1 - X_COORD PASSED");
        total_grade = total_grade + 1;
    end else begin
        $display("[FAIL] TEST A1 - X_COORD FAILED");
    end
    if (Y_COORD == 0) begin
        $display("[OK] TEST A1 - Y_COORD PASSED");
        total_grade = total_grade + 1;
    end else begin
        $display("[FAIL] TEST A1 - Y_COORD FAILED");
    end

    #FP;
    START = 0;
    DIRECTION = 0;
    INIT_Y_POS = 0;

    if (X_COORD == 0) begin
        $display("[OK] TEST A2 - X_COORD PASSED");
        total_grade = total_grade + 1;
    end else begin
        $display("[FAIL] TEST A2 - X_COORD FAILED");
    end
    if (Y_COORD == 0) begin
        $display("[OK] TEST A2 - Y_COORD PASSED");
        total_grade = total_grade + 1;
    end else begin
        $display("[FAIL] TEST A2 - Y_COORD FAILED");
    end

#FP;

    if (X_COORD == 1) begin
        $display("[OK] TEST A3 - X_COORD PASSED");
        total_grade = total_grade + 1;
    end else begin
        $display("[FAIL] TEST A3 - X_COORD FAILED");
    end
    if (Y_COORD == 0) begin
        $display("[OK] TEST A3 - Y_COORD PASSED");
        total_grade = total_grade + 1;
    end else begin
        $display("[FAIL] TEST A3 - Y_COORD FAILED");
    end

#FP;

    if (X_COORD == 2) begin
        $display("[OK] TEST A4 - X_COORD PASSED");
        total_grade = total_grade + 1;
    end else begin
        $display("[FAIL] TEST A4 - X_COORD FAILED");
    end
    if (Y_COORD == 0) begin
        $display("[OK] TEST A4 - Y_COORD PASSED");
        total_grade = total_grade + 1;
    end else begin
        $display("[FAIL] TEST A4 - Y_COORD FAILED");
    end

#FP;

    if (X_COORD == 3) begin
        $display("[OK] TEST A5 - X_COORD PASSED");
        total_grade = total_grade + 1;
    end else begin
        $display("[FAIL] TEST A5 - X_COORD FAILED");
    end
    if (Y_COORD == 0) begin
        $display("[OK] TEST A5 - Y_COORD PASSED");
        total_grade = total_grade + 1;
    end else begin
        $display("[FAIL] TEST A5 - Y_COORD FAILED");
    end

#FP;

    if (X_COORD == 4) begin
        $display("[OK] TEST A6 - X_COORD PASSED");
        total_grade = total_grade + 1;
    end else begin
        $display("[FAIL] TEST A6 - X_COORD FAILED");
    end
    if (Y_COORD == 0) begin
        $display("[OK] TEST A6 - Y_COORD PASSED");
        total_grade = total_grade + 1;
    end else begin
        $display("[FAIL] TEST A6 - Y_COORD FAILED");
    end

#FP;

    if (X_COORD == 3) begin
        $display("[OK] TEST A7 - X_COORD PASSED");
        total_grade = total_grade + 1;
    end else begin
        $display("[FAIL] TEST A7 - X_COORD FAILED");
    end
    if (Y_COORD == 0) begin
        $display("[OK] TEST A7 - Y_COORD PASSED");
        total_grade = total_grade + 1;
    end else begin
        $display("[FAIL] TEST A7 - Y_COORD FAILED");
    end

#FP;

    if (X_COORD == 2) begin
        $display("[OK] TEST A8 - X_COORD PASSED");
        total_grade = total_grade + 1;
    end else begin
        $display("[FAIL] TEST A8 - X_COORD FAILED");
    end
    if (Y_COORD == 0) begin
        $display("[OK] TEST A8 - Y_COORD PASSED");
        total_grade = total_grade + 1;
    end else begin
        $display("[FAIL] TEST A8 - Y_COORD FAILED");
    end

#FP;

    if (X_COORD == 1) begin
        $display("[OK] TEST A9 - X_COORD PASSED");
        total_grade = total_grade + 1;
    end else begin
        $display("[FAIL] TEST A9 - X_COORD FAILED");
    end
    if (Y_COORD == 0) begin
        $display("[OK] TEST A9 - Y_COORD PASSED");
        total_grade = total_grade + 1;
    end else begin
        $display("[FAIL] TEST A9 - Y_COORD FAILED");
    end

#FP;

// Test Suite B

    #FP;
    rst = 1;
    #FP; // Wait a full clock period to pass
    rst = 0;
    START = 1;
    DIRECTION = 1;
    INIT_Y_POS = 3;
    
    
    if (X_COORD == 0) begin
        $display("[OK] TEST B1 - X_COORD PASSED");
        total_grade = total_grade + 1;
    end else begin
        $display("[FAIL] TEST B1 - X_COORD FAILED");
    end
    if (Y_COORD == 0) begin
        $display("[OK] TEST B1 - Y_COORD PASSED");
        total_grade = total_grade + 1;
    end else begin
        $display("[FAIL] TEST B1 - Y_COORD FAILED");
    end

    #FP;
    START = 0;
    DIRECTION = 0;
    INIT_Y_POS = 0;

    if (X_COORD == 0) begin
        $display("[OK] TEST B2 - X_COORD PASSED");
        total_grade = total_grade + 1;
    end else begin
        $display("[FAIL] TEST B2 - X_COORD FAILED");
    end
    if (Y_COORD == 3) begin
        $display("[OK] TEST B2 - Y_COORD PASSED");
        total_grade = total_grade + 1;
    end else begin
        $display("[FAIL] TEST B2 - Y_COORD FAILED");
    end

#FP;

    if (X_COORD == 1) begin
        $display("[OK] TEST B3 - X_COORD PASSED");
        total_grade = total_grade + 1;
    end else begin
        $display("[FAIL] TEST B3 - X_COORD FAILED");
    end
    if (Y_COORD == 4) begin
        $display("[OK] TEST B3 - Y_COORD PASSED");
        total_grade = total_grade + 1;
    end else begin
        $display("[FAIL] TEST B3 - Y_COORD FAILED");
    end

#FP;

    if (X_COORD == 2) begin
        $display("[OK] TEST B4 - X_COORD PASSED");
        total_grade = total_grade + 1;
    end else begin
        $display("[FAIL] TEST B4 - X_COORD FAILED");
    end
    if (Y_COORD == 3) begin
        $display("[OK] TEST B4 - Y_COORD PASSED");
        total_grade = total_grade + 1;
    end else begin
        $display("[FAIL] TEST B4 - Y_COORD FAILED");
    end

#FP;

    if (X_COORD == 3) begin
        $display("[OK] TEST B5 - X_COORD PASSED");
        total_grade = total_grade + 1;
    end else begin
        $display("[FAIL] TEST B5 - X_COORD FAILED");
    end
    if (Y_COORD == 2) begin
        $display("[OK] TEST B5 - Y_COORD PASSED");
        total_grade = total_grade + 1;
    end else begin
        $display("[FAIL] TEST B5 - Y_COORD FAILED");
    end

#FP;

    if (X_COORD == 4) begin
        $display("[OK] TEST B6 - X_COORD PASSED");
        total_grade = total_grade + 1;
    end else begin
        $display("[FAIL] TEST B6 - X_COORD FAILED");
    end
    if (Y_COORD == 1) begin
        $display("[OK] TEST B6 - Y_COORD PASSED");
        total_grade = total_grade + 1;
    end else begin
        $display("[FAIL] TEST B6 - Y_COORD FAILED");
    end

#FP;

    if (X_COORD == 3) begin
        $display("[OK] TEST B7 - X_COORD PASSED");
        total_grade = total_grade + 1;
    end else begin
        $display("[FAIL] TEST B7 - X_COORD FAILED");
    end
    if (Y_COORD == 0) begin
        $display("[OK] TEST B7 - Y_COORD PASSED");
        total_grade = total_grade + 1;
    end else begin
        $display("[FAIL] TEST B7 - Y_COORD FAILED");
    end

#FP;

    if (X_COORD == 2) begin
        $display("[OK] TEST B8 - X_COORD PASSED");
        total_grade = total_grade + 1;
    end else begin
        $display("[FAIL] TEST B8 - X_COORD FAILED");
    end
    if (Y_COORD == 1) begin
        $display("[OK] TEST B8 - Y_COORD PASSED");
        total_grade = total_grade + 1;
    end else begin
        $display("[FAIL] TEST B8 - Y_COORD FAILED");
    end

#FP;

    if (X_COORD == 1) begin
        $display("[OK] TEST B9 - X_COORD PASSED");
        total_grade = total_grade + 1;
    end else begin
        $display("[FAIL] TEST B9 - X_COORD FAILED");
    end
    if (Y_COORD == 2) begin
        $display("[OK] TEST B9 - Y_COORD PASSED");
        total_grade = total_grade + 1;
    end else begin
        $display("[FAIL] TEST B9 - Y_COORD FAILED");
    end

#FP;

// Test Suite C

    #FP;
    rst = 1;
    #FP; // Wait a full clock period to pass
    rst = 0;
    START = 1;
    DIRECTION = 2;
    INIT_Y_POS = 1;
    
    
    if (X_COORD == 0) begin
        $display("[OK] TEST C1 - X_COORD PASSED");
        total_grade = total_grade + 1;
    end else begin
        $display("[FAIL] TEST C1 - X_COORD FAILED");
    end
    if (Y_COORD == 0) begin
        $display("[OK] TEST C1 - Y_COORD PASSED");
        total_grade = total_grade + 1;
    end else begin
        $display("[FAIL] TEST C1 - Y_COORD FAILED");
    end

    #FP;
    START = 0;
    DIRECTION = 0;
    INIT_Y_POS = 0;

    if (X_COORD == 0) begin
        $display("[OK] TEST C2 - X_COORD PASSED");
        total_grade = total_grade + 1;
    end else begin
        $display("[FAIL] TEST C2 - X_COORD FAILED");
    end
    if (Y_COORD == 1) begin
        $display("[OK] TEST C2 - Y_COORD PASSED");
        total_grade = total_grade + 1;
    end else begin
        $display("[FAIL] TEST C2 - Y_COORD FAILED");
    end

#FP;

    if (X_COORD == 1) begin
        $display("[OK] TEST C3 - X_COORD PASSED");
        total_grade = total_grade + 1;
    end else begin
        $display("[FAIL] TEST C3 - X_COORD FAILED");
    end
    if (Y_COORD == 0) begin
        $display("[OK] TEST C3 - Y_COORD PASSED");
        total_grade = total_grade + 1;
    end else begin
        $display("[FAIL] TEST C3 - Y_COORD FAILED");
    end

#FP;

    if (X_COORD == 2) begin
        $display("[OK] TEST C4 - X_COORD PASSED");
        total_grade = total_grade + 1;
    end else begin
        $display("[FAIL] TEST C4 - X_COORD FAILED");
    end
    if (Y_COORD == 1) begin
        $display("[OK] TEST C4 - Y_COORD PASSED");
        total_grade = total_grade + 1;
    end else begin
        $display("[FAIL] TEST C4 - Y_COORD FAILED");
    end

#FP;

    if (X_COORD == 3) begin
        $display("[OK] TEST C5 - X_COORD PASSED");
        total_grade = total_grade + 1;
    end else begin
        $display("[FAIL] TEST C5 - X_COORD FAILED");
    end
    if (Y_COORD == 2) begin
        $display("[OK] TEST C5 - Y_COORD PASSED");
        total_grade = total_grade + 1;
    end else begin
        $display("[FAIL] TEST C5 - Y_COORD FAILED");
    end

#FP;

    if (X_COORD == 4) begin
        $display("[OK] TEST C6 - X_COORD PASSED");
        total_grade = total_grade + 1;
    end else begin
        $display("[FAIL] TEST C6 - X_COORD FAILED");
    end
    if (Y_COORD == 3) begin
        $display("[OK] TEST C6 - Y_COORD PASSED");
        total_grade = total_grade + 1;
    end else begin
        $display("[FAIL] TEST C6 - Y_COORD FAILED");
    end

#FP;

    if (X_COORD == 3) begin
        $display("[OK] TEST C7 - X_COORD PASSED");
        total_grade = total_grade + 1;
    end else begin
        $display("[FAIL] TEST C7 - X_COORD FAILED");
    end
    if (Y_COORD == 4) begin
        $display("[OK] TEST C7 - Y_COORD PASSED");
        total_grade = total_grade + 1;
    end else begin
        $display("[FAIL] TEST C7 - Y_COORD FAILED");
    end

#FP;

    if (X_COORD == 2) begin
        $display("[OK] TEST C8 - X_COORD PASSED");
        total_grade = total_grade + 1;
    end else begin
        $display("[FAIL] TEST C8 - X_COORD FAILED");
    end
    if (Y_COORD == 3) begin
        $display("[OK] TEST C8 - Y_COORD PASSED");
        total_grade = total_grade + 1;
    end else begin
        $display("[FAIL] TEST C8 - Y_COORD FAILED");
    end

#FP;

    if (X_COORD == 1) begin
        $display("[OK] TEST C9 - X_COORD PASSED");
        total_grade = total_grade + 1;
    end else begin
        $display("[FAIL] TEST C9 - X_COORD FAILED");
    end
    if (Y_COORD == 2) begin
        $display("[OK] TEST C9 - Y_COORD PASSED");
        total_grade = total_grade + 1;
    end else begin
        $display("[FAIL] TEST C9 - Y_COORD FAILED");
    end

#FP;

// Test Suite D

    #FP;
    rst = 1;
    #FP; // Wait a full clock period to pass
    rst = 0;
    START = 1;
    DIRECTION = 1;
    INIT_Y_POS = 0;
    
    
    if (X_COORD == 0) begin
        $display("[OK] TEST D1 - X_COORD PASSED");
        total_grade = total_grade + 1;
    end else begin
        $display("[FAIL] TEST D1 - X_COORD FAILED");
    end
    if (Y_COORD == 0) begin
        $display("[OK] TEST D1 - Y_COORD PASSED");
        total_grade = total_grade + 1;
    end else begin
        $display("[FAIL] TEST D1 - Y_COORD FAILED");
    end

    #FP;
    START = 0;
    DIRECTION = 0;
    INIT_Y_POS = 0;

    if (X_COORD == 0) begin
        $display("[OK] TEST D2 - X_COORD PASSED");
        total_grade = total_grade + 1;
    end else begin
        $display("[FAIL] TEST D2 - X_COORD FAILED");
    end
    if (Y_COORD == 0) begin
        $display("[OK] TEST D2 - Y_COORD PASSED");
        total_grade = total_grade + 1;
    end else begin
        $display("[FAIL] TEST D2 - Y_COORD FAILED");
    end

#FP;

    if (X_COORD == 1) begin
        $display("[OK] TEST D3 - X_COORD PASSED");
        total_grade = total_grade + 1;
    end else begin
        $display("[FAIL] TEST D3 - X_COORD FAILED");
    end
    if (Y_COORD == 1) begin
        $display("[OK] TEST D3 - Y_COORD PASSED");
        total_grade = total_grade + 1;
    end else begin
        $display("[FAIL] TEST D3 - Y_COORD FAILED");
    end

#FP;

    if (X_COORD == 2) begin
        $display("[OK] TEST D4 - X_COORD PASSED");
        total_grade = total_grade + 1;
    end else begin
        $display("[FAIL] TEST D4 - X_COORD FAILED");
    end
    if (Y_COORD == 2) begin
        $display("[OK] TEST D4 - Y_COORD PASSED");
        total_grade = total_grade + 1;
    end else begin
        $display("[FAIL] TEST D4 - Y_COORD FAILED");
    end

#FP;

    if (X_COORD == 3) begin
        $display("[OK] TEST D5 - X_COORD PASSED");
        total_grade = total_grade + 1;
    end else begin
        $display("[FAIL] TEST D5 - X_COORD FAILED");
    end
    if (Y_COORD == 3) begin
        $display("[OK] TEST D5 - Y_COORD PASSED");
        total_grade = total_grade + 1;
    end else begin
        $display("[FAIL] TEST D5 - Y_COORD FAILED");
    end

#FP;

    if (X_COORD == 4) begin
        $display("[OK] TEST D6 - X_COORD PASSED");
        total_grade = total_grade + 1;
    end else begin
        $display("[FAIL] TEST D6 - X_COORD FAILED");
    end
    if (Y_COORD == 4) begin
        $display("[OK] TEST D6 - Y_COORD PASSED");
        total_grade = total_grade + 1;
    end else begin
        $display("[FAIL] TEST D6 - Y_COORD FAILED");
    end

#FP;

    if (X_COORD == 3) begin
        $display("[OK] TEST D7 - X_COORD PASSED");
        total_grade = total_grade + 1;
    end else begin
        $display("[FAIL] TEST D7 - X_COORD FAILED");
    end
    if (Y_COORD == 3) begin
        $display("[OK] TEST D7 - Y_COORD PASSED");
        total_grade = total_grade + 1;
    end else begin
        $display("[FAIL] TEST D7 - Y_COORD FAILED");
    end

#FP;

    if (X_COORD == 2) begin
        $display("[OK] TEST D8 - X_COORD PASSED");
        total_grade = total_grade + 1;
    end else begin
        $display("[FAIL] TEST D8 - X_COORD FAILED");
    end
    if (Y_COORD == 2) begin
        $display("[OK] TEST D8 - Y_COORD PASSED");
        total_grade = total_grade + 1;
    end else begin
        $display("[FAIL] TEST D8 - Y_COORD FAILED");
    end

#FP;

    if (X_COORD == 1) begin
        $display("[OK] TEST D9 - X_COORD PASSED");
        total_grade = total_grade + 1;
    end else begin
        $display("[FAIL] TEST D9 - X_COORD FAILED");
    end
    if (Y_COORD == 1) begin
        $display("[OK] TEST D9 - Y_COORD PASSED");
        total_grade = total_grade + 1;
    end else begin
        $display("[FAIL] TEST D9 - Y_COORD FAILED");
    end

#FP;

    $display("Total Grade is %d" , total_grade);
    $display("Simulation finished.");
    $finish(); // Finish simulation.
end



endmodule

LAB4/DigiHockey.vcd
$date
	Tue Dec 19 14:08:42 2023
$end
$version
	Icarus Verilog
$end
$timescale
	1s
$end
$scope module DigiHockey_tb $end
$var wire 3 ! Y_COORD [2:0] $end
$var wire 3 " X_COORD [2:0] $end
$var parameter 64 # FP $end
$var parameter 32 $ HP $end
$var reg 2 % DIRECTION [1:0] $end
$var reg 3 & INIT_Y_POS [2:0] $end
$var reg 1 ' START $end
$var reg 1 ( clk $end
$var reg 1 ) rst $end
$var integer 32 * total_grade [31:0] $end
$scope module dut $end
$var wire 2 + DIRECTION [1:0] $end
$var wire 3 , INIT_Y_POS [2:0] $end
$var wire 1 ' START $end
$var wire 1 ( clk $end
$var wire 1 ) rst $end
$var reg 3 - X_COORD [2:0] $end
$var reg 3 . Y_COORD [2:0] $end
$var reg 2 / direction_reg [1:0] $end
$var reg 1 0 isMovingRight $end
$var reg 2 1 isMovingUp [1:0] $end
$var reg 1 2 started $end
$upscope $end
$upscope $end
$enddefinitions $end
$comment Show the parameter values. $end
$dumpall
b101 $
b1010 #
$end
#0
$dumpvars
x2
bx 1
x0
bx /
bx .
bx -
b0 ,
b0 +
b1010 *
0)
0(
0'
b0 &
b0 %
bx "
bx !
$end
#5
1(
#10
b0 /
b10 1
10
b0 "
b0 -
b0 !
b0 .
0(
1)
#15
1(
#20
0(
b1100 *
1'
0)
#25
12
1(
#30
0(
b1110 *
0'
#35
b1 "
b1 -
1(
#40
0(
b10000 *
#45
b10 "
b10 -
1(
#50
0(
b10010 *
#55
b11 "
b11 -
1(
#60
0(
b10100 *
#65
b100 "
b100 -
1(
#70
0(
b10110 *
#75
00
b11 "
b11 -
1(
#80
0(
b11000 *
#85
b10 "
b10 -
1(
#90
0(
b11010 *
#95
b1 "
b1 -
1(
#100
0(
b11100 *
#105
b0 "
b0 -
1(
#110
0(
#115
10
b1 "
b1 -
1(
#120
b0 "
b0 -
0(
1)
#125
1(
#130
0(
b11110 *
b11 &
b11 ,
b1 %
b1 +
1'
0)
#135
b1 1
b11 !
b11 .
1(
#140
0(
b100000 *
b0 &
b0 ,
b0 %
b0 +
0'
#145
b100 !
b100 .
b1 "
b1 -
1(
#150
0(
b100010 *
#155
b0 1
b11 !
b11 .
b10 "
b10 -
1(
#160
0(
b100100 *
#165
b10 !
b10 .
b11 "
b11 -
1(
#170
0(
b100110 *
#175
b1 !
b1 .
b100 "
b100 -
1(
#180
0(
b101000 *
#185
b0 !
b0 .
00
b11 "
b11 -
1(
#190
0(
b101010 *
#195
b1 1
b1 !
b1 .
b10 "
b10 -
1(
#200
0(
b101100 *
#205
b10 !
b10 .
b1 "
b1 -
1(
#210
0(
b101110 *
#215
b11 !
b11 .
b0 "
b0 -
1(
#220
0(
#225
b100 !
b100 .
10
b1 "
b1 -
1(
#230
b10 1
b0 "
b0 -
b0 !
b0 .
0(
1)
#235
1(
#240
0(
b110000 *
b1 &
b1 ,
b10 %
b10 +
1'
0)
#245
b0 1
b1 !
b1 .
1(
#250
0(
b110010 *
b0 &
b0 ,
b0 %
b0 +
0'
#255
b0 !
b0 .
b1 "
b1 -
1(
#260
0(
b110100 *
#265
b1 1
b1 !
b1 .
b10 "
b10 -
1(
#270
0(
b110110 *
#275
b10 !
b10 .
b11 "
b11 -
1(
#280
0(
b111000 *
#285
b11 !
b11 .
b100 "
b100 -
1(
#290
0(
b111010 *
#295
b100 !
b100 .
00
b11 "
b11 -
1(
#300
0(
b111100 *
#305
b0 1
b11 !
b11 .
b10 "
b10 -
1(
#310
0(
b111110 *
#315
b10 !
b10 .
b1 "
b1 -
1(
#320
0(
b1000000 *
#325
b1 !
b1 .
b0 "
b0 -
1(
#330
0(
#335
b0 !
b0 .
10
b1 "
b1 -
1(
#340
b10 1
b0 "
b0 -
0(
1)
#345
1(
#350
0(
b1000010 *
b1 %
b1 +
1'
0)
#355
b1 1
1(
#360
0(
b1000100 *
b0 %
b0 +
0'
#365
b1 !
b1 .
b1 "
b1 -
1(
#370
0(
b1000110 *
#375
b10 !
b10 .
b10 "
b10 -
1(
#380
0(
b1001000 *
#385
b11 !
b11 .
b11 "
b11 -
1(
#390
0(
b1001010 *
#395
b100 !
b100 .
b100 "
b100 -
1(
#400
0(
b1001100 *
#405
b0 1
b11 !
b11 .
00
b11 "
b11 -
1(
#410
0(
b1001110 *
#415
b10 !
b10 .
b10 "
b10 -
1(
#420
0(
b1010000 *
#425
b1 !
b1 .
b1 "
b1 -
1(
#430
0(
b1010010 *
#435
b0 !
b0 .
b0 "
b0 -
1(
