LAB2/LAB1_CS303.v
/*
 * Generated by Digital. Don't modify this file!
 * Any changes will be lost if this file is regenerated.
 */

module LAB1_CS303 (
  input x3,
  input x2,
  input x1,
  input x0,
  output out
);
  assign out = ((~ x3 & ~ x2 & x1) | (~ x3 & x2 & x0) | (x2 & ~ x1 & x0) | (~ x2 & x1 & x0));
endmodule

LAB2/LAB1_CS303_tb.v
module LAB1_CS303_tb();

reg x3,x2,x1,x0;  // Inputs are registers.
wire out;   // Outputs are wires.

LAB1_CS303 dut(x3, x2, x1, x0, out); // Our design-under-test.

initial begin
    //  * Our waveform is saved under this file.
    
    $dumpfile("LAB1_CS303.vcd"); 
    
    // * Get the variables from the module.

    $dumpvars(0,LAB1_CS303_tb);

    $display("Simulation started.");
     
    x0 = 0;  //1.case
    x1 = 0;
    x2 = 0;
    x3 = 0;

    #10;

    x0 = 1;  //2.case
    x1 = 0;
    x2 = 0;
    x3 = 0;
    
    #10;

    x0 = 0;  //3.case
    x1 = 1;
    x2 = 0;
    x3 = 0;
    
    #10;

    x0 = 1;  //4.case
    x1 = 1;
    x2 = 0;
    x3 = 0;
    
    #10;

    x0 = 0;  //5.case
    x1 = 0;
    x2 = 1;
    x3 = 0;
    
    #10;

    x0 = 1;  //6.case
    x1 = 0;
    x2 = 1;
    x3 = 0;

    #10;

    x0 = 0;  //7.case
    x1 = 1;
    x2 = 1;
    x3 = 0;
     
    #10; 

    x0 = 1;  //8.case
    x1 = 1;
    x2 = 1;
    x3 = 0;
     
    #10; 

    x0 = 0;  //9.case
    x1 = 0;
    x2 = 0;
    x3 = 1;
     
    #10; 

    x0 = 1;  //10.case
    x1 = 0;
    x2 = 0;
    x3 = 1;
     
    #10; 

    x0 = 0;  //11.case
    x1 = 1;
    x2 = 0;
    x3 = 1;
     
    #10; 

    x0 = 1;  //12.case
    x1 = 1;
    x2 = 0;
    x3 = 1;
     
    #10; 

    x0 = 0;  //13.case
    x1 = 0;
    x2 = 1;
    x3 = 1;
     
    #10; 

    x0 = 1;  //14.case
    x1 = 0;
    x2 = 1;
    x3 = 1;
     
    #10; 

    x0 = 0;  //15.case
    x1 = 1;
    x2 = 1;
    x3 = 1;
     
    #10; 

    x0 = 1;  //16.case
    x1 = 1;
    x2 = 1;
    x3 = 1;
    
    #10;
     
    
    $display("Simulation finished.");
    $finish(); // Finish simulation.
end

endmodule

LAB2/LAB1_CS303.vcd
$date
	Tue Nov 21 13:52:23 2023
$end
$version
	Icarus Verilog
$end
$timescale
	1s
$end
$scope module LAB1_CS303_tb $end
$var wire 1 ! out $end
$var reg 1 " x0 $end
$var reg 1 # x1 $end
$var reg 1 $ x2 $end
$var reg 1 % x3 $end
$scope module dut $end
$var wire 1 ! out $end
$var wire 1 " x0 $end
$var wire 1 # x1 $end
$var wire 1 $ x2 $end
$var wire 1 % x3 $end
$upscope $end
$upscope $end
$enddefinitions $end
$comment Show the parameter values. $end
$dumpall
$end
#0
$dumpvars
0%
0$
0#
0"
0!
$end
#10
1"
#20
1!
1#
0"
#30
1"
#40
0!
1$
0#
0"
#50
1!
1"
#60
0!
1#
0"
#70
1!
1"
#80
0!
1%
0$
0#
0"
#90
1"
#100
1#
0"
#110
1!
1"
#120
0!
1$
0#
0"
#130
1!
1"
#140
0!
1#
0"
#150
1"
