LAB3/CLA_4bit.v
module CLA_4bit 
  (
   input  [3:0]           C,
   input  [3:0]           D,
   input                  Cin,
   input                  mode, // 0 --> addition , 1 --> subtraction          
   output [3:0]           RES,
   output                 Carry
   );

  wire [3:0] P,G; //for the generate and propogate
  wire [4:0] CarryOut; // for each of the carries including cin i.e c0

  //the logic behind the operation below is coming from the lecture slides, "Subtractor" part, while assigning G and P, we take one input's 
  //xor with mode value

  assign G[0] = C[0] & ( D[0] ^ mode ); //and operation is used for the generate signal
  assign G[1] = C[1] & ( D[1] ^ mode );
  assign G[2] = C[2] & ( D[2] ^ mode );
  assign G[3] = C[3] & ( D[3] ^ mode );

  assign P[0] = C[0] ^ ( D[0] ^ mode ); //xor operation is used for the propogate signal
  assign P[1] = C[1] ^ ( D[1] ^ mode );
  assign P[2] = C[2] ^ ( D[2] ^ mode );
  assign P[3] = C[3] ^ ( D[3] ^ mode );

  assign CarryOut[0] = Cin; //C0 is inputted

  //these are the simplified operations of each carry out signal

  assign CarryOut[1] = G[0] | (Cin & P[0]);           //G0 + (P0·C0) 
  assign CarryOut[2] = G[1] | (P[1] & CarryOut[1]);   //G1 + (P1·C1)
  assign CarryOut[3] = G[2] | (P[2] & CarryOut[2]);   //G2 + (P2·C2)
  assign CarryOut[4] = G[3] | (P[3] & CarryOut[3]);   //G3 + (P3·C3)

  assign Carry = CarryOut[4]; //we assign the last adder's carry to our main output carry

  assign RES[0] = P[0] ^ CarryOut[0]; //then we assign each bit of the result with the xor of propogate and carry
  assign RES[1] = P[1] ^ CarryOut[1];
  assign RES[2] = P[2] ^ CarryOut[2];
  assign RES[3] = P[3] ^ CarryOut[3];

endmodule

LAB3/CLA_16bit_top.v
`include "CLA_4bit.v" 

module CLA_16bit_top 
    (
        input   [15:0]          A,
        input   [15:0]          B,
        input                   mode, // 0 --> addition , 1 --> subtraction
        output  [15:0]          S,
        output                  Cout,
        output                  OVF
    );    

    wire [3:0] Carry_Out; //a 4 bit carry out signal, to insert one cla's output carry to others input


    //these are the declarations of our 4 bit cla's. Directly taken from lecture slides. Modified the first cin as the mode signal,
    //as it is mandatory to not have a minus 1 in subtraction operation

    CLA_4bit CLA_1 (.C(A[3:0]), .D(B[3:0]), .Cin(mode), .mode(mode), .RES(S[3:0]), .Carry(Carry_Out[0]));
    CLA_4bit CLA_2 (.C(A[7:4]), .D(B[7:4]), .Cin(Carry_Out[0]), .mode(mode), .RES(S[7:4]), .Carry(Carry_Out[1]));
    CLA_4bit CLA_3 (.C(A[11:8]), .D(B[11:8]), .Cin(Carry_Out[1]), .mode(mode), .RES(S[11:8]), .Carry(Carry_Out[2]));
    CLA_4bit CLA_4 (.C(A[15:12]), .D(B[15:12]), .Cin(Carry_Out[2]), .mode(mode), .RES(S[15:12]), .Carry(Carry_Out[3]));

    assign Cout = Carry_Out[3]; //assigning the last carry to our cout signal.

    //the overflow detection is tried to be implemented according to the overflow detection page in the lecture slides page 51, i used the second approach
    //since i don't wanted to use if-else statements, i used ternary operator, if the circuit acts as an adder, first part is executed, else the right part.
    
    assign OVF = (mode == 0) ? ((A[15] & B[15] & ~S[15]) | (~A[15] & ~B[15] & S[15])) : ((A[15] & ~B[15] & ~S[15]) | (~A[15] & B[15] & S[15]));


        

 
endmodule

LAB3/CLA_16bit_tb.v
module CLA_16bit_tb();

reg  [15:0]         A, B; // Inputs
reg                 mode;  // mode (add or subtract)
wire [15:0]         S; // result
wire                Ovf;   // Outputs are wires.
wire                Cout;

CLA_16bit_top dut(A, B, mode, S, Cout ,Ovf); // Our design-under-test.

initial begin
    //  * Our waveform is saved under this file.
    
    $dumpfile("CLA_16bit_top.vcd"); 
    
    // * Get the variables from the module.

    $dumpvars(0,CLA_16bit_tb);

    $display("Simulation started.");

    
    //Case 1, addition without a carry and without an overflow:

    A = 16'd25;
    B = 16'd10;
    mode = 1'b0;
    #10;

    //Case 2, addition without a carry and with an overflow:

    A = 16'd32760;
    B = 16'd50;
    mode = 1'b0;
    #10;

    //Case 3, addition with a carry and without an overflow:

    A = 16'd32000;
    B = 16'd16000;
    mode = 1'b0;
    #10;

    //Case 4, addition with a carry and with an overflow:

    A = 16'd32767;
    B = 16'd2;
    mode = 1'b0;
    #10;

    //Case 5, subtraction without a carry and without an overflow:

    A = 16'd40;
    B = 16'd10;
    mode = 1'b1;
    #10;

    //Case 6, subtraction without a carry and with an overflow:

    A = 16'd10;
    B = 16'd20;
    mode = 1'b1;
    #10;

    //Case 7, subtraction with a carry and without an overflow:

    A = 16'd500;
    B = 16'd100;
    mode = 1'b1;
    #10;

    //Case 8, subtraction with a carry and with an overflow:

    A = 16'd20;
    B = 16'd50;
    mode = 1'b1;
    #10;
    
    $display("Simulation finished.");
    $finish(); // Finish simulation.
end

endmodule

LAB3/CLA_16bit_top.vcd
$date
	Sun Dec  3 22:31:46 2023
$end
$version
	Icarus Verilog
$end
$timescale
	1s
$end
$scope module CLA_16bit_tb $end
$var wire 16 ! S [15:0] $end
$var wire 1 " Ovf $end
$var wire 1 # Cout $end
$var reg 16 $ A [15:0] $end
$var reg 16 % B [15:0] $end
$var reg 1 & mode $end
$scope module dut $end
$var wire 16 ' A [15:0] $end
$var wire 16 ( B [15:0] $end
$var wire 1 & mode $end
$var wire 16 ) S [15:0] $end
$var wire 1 " OVF $end
$var wire 1 # Cout $end
$var wire 4 * Carry_Out [3:0] $end
$scope module CLA_1 $end
$var wire 4 + C [3:0] $end
$var wire 1 & Cin $end
$var wire 4 , D [3:0] $end
$var wire 1 & mode $end
$var wire 4 - RES [3:0] $end
$var wire 4 . P [3:0] $end
$var wire 4 / G [3:0] $end
$var wire 5 0 CarryOut [4:0] $end
$var wire 1 1 Carry $end
$upscope $end
$scope module CLA_2 $end
$var wire 4 2 C [3:0] $end
$var wire 1 3 Cin $end
$var wire 4 4 D [3:0] $end
$var wire 1 & mode $end
$var wire 4 5 RES [3:0] $end
$var wire 4 6 P [3:0] $end
$var wire 4 7 G [3:0] $end
$var wire 5 8 CarryOut [4:0] $end
$var wire 1 9 Carry $end
$upscope $end
$scope module CLA_3 $end
$var wire 4 : C [3:0] $end
$var wire 1 ; Cin $end
$var wire 4 < D [3:0] $end
$var wire 1 & mode $end
$var wire 4 = RES [3:0] $end
$var wire 4 > P [3:0] $end
$var wire 4 ? G [3:0] $end
$var wire 5 @ CarryOut [4:0] $end
$var wire 1 A Carry $end
$upscope $end
$scope module CLA_4 $end
$var wire 4 B C [3:0] $end
$var wire 1 C Cin $end
$var wire 4 D D [3:0] $end
$var wire 1 & mode $end
$var wire 4 E RES [3:0] $end
$var wire 4 F P [3:0] $end
$var wire 4 G G [3:0] $end
$var wire 5 H CarryOut [4:0] $end
$var wire 1 I Carry $end
$upscope $end
$upscope $end
$upscope $end
$enddefinitions $end
$comment Show the parameter values. $end
$dumpall
$end
#0
$dumpvars
0I
b0 H
b0 G
b0 F
b0 E
b0 D
0C
b0 B
0A
b0 @
b0 ?
b0 >
b0 =
b0 <
0;
b0 :
09
b11 8
b0 7
b1 6
b10 5
b0 4
13
b1 2
11
b10000 0
b1000 /
b11 .
b11 -
b1010 ,
b1001 +
b1 *
b100011 )
b1010 (
b11001 '
0&
b1010 %
b11001 $
0#
0"
b100011 !
$end
#10
1"
b1111 H
1C
1A
b11111 @
1;
19
03
b110 *
01
b0 0
b11110 8
b1010 -
b10 5
b0 =
b1000000000101010 !
b1000000000101010 )
b1000 E
b0 /
b11 7
b1010 .
b1100 6
b1111 >
b111 F
b10 ,
b11 4
b1000 +
b1111 2
b1111 :
b111 B
b110010 %
b110010 (
b111111111111000 $
b111111111111000 '
#20
0;
b100 *
09
b1011 E
b11000 @
b0 -
b0 8
b1000 5
b1011101110000000 !
b1011101110000000 )
b1011 =
b1100 ?
b11 G
b100 F
b0 .
b0 7
b1000 6
b11 >
b0 ,
b1000 4
b1110 <
b11 D
b0 +
b0 2
b1101 :
b11111010000000 %
b11111010000000 (
b111110100000000 $
b111110100000000 '
#30
1"
13
b1111 H
1C
11
1A
1;
b11100 0
b1000 E
b111 *
19
b1 -
b11111 8
b0 5
b11111 @
b1000000000000001 !
b1000000000000001 )
b0 =
b10 /
b0 G
b111 F
b1101 .
b0 7
b1111 6
b0 ?
b1111 >
b10 ,
b0 4
b0 <
b0 D
b1111 +
b1111 2
b1111 :
b10 %
b10 (
b111111111111111 $
b111111111111111 '
#40
b11100 8
03
01
1#
b1110 *
1I
b11111 H
b1 5
b0 E
b0 /
b1101 .
b11110 !
b11110 )
b1110 -
b10 7
b1101 6
b1111 F
0"
b1010 ,
b1000 +
b10 2
b0 :
b0 B
b11 0
1&
b1010 %
b1010 (
b101000 $
b101000 '
#50
0#
0I
b1111 E
b0 H
0C
0A
b1111 =
b0 @
0;
09
13
b1 *
11
b10111 0
b110 -
b1 8
b1111111111110110 !
b1111111111110110 )
b1111 5
b1010 /
b1 .
b0 7
b1110 6
b100 ,
b1 4
b1010 +
b0 2
b10100 %
b10100 (
b1010 $
b1010 '
#60
1#
1I
b0 E
b11111 H
1C
1A
13
1;
11
b1111 *
19
b11111 0
b0 -
b11111 8
b1001 5
b11111 @
b110010000 !
b110010000 )
b1 =
b0 /
b1111 .
b1001 7
b110 6
b1 ?
b1110 >
b110 4
b100 +
b1111 2
b1 :
b1100100 %
b1100100 (
b111110100 $
b111110100 '
#70
0#
0I
b1111 E
b0 H
0C
0A
b0 @
0;
b1 *
09
b11011 0
b10 -
b11 8
b1110 5
b1111111111100010 !
b1111111111100010 )
b1111 =
b100 /
b1001 .
b0 7
b1101 6
b0 ?
b1111 >
b10 ,
b11 4
b1 2
b0 :
b110010 %
b110010 (
b10100 $
b10100 '
